{
  "SERCODIGO": "BM12_TJOVER12",
  "SERNOME": "Taxa de juros - Over / Selic",
  "SERCOMENTARIO": "Quadro: Taxas de juros efetivas.  Para 1974-1979: fonte Andima.  Dados mais recentes atualizados pela Sinopse da Andima.  Obs.: A taxa Overnight / Selic é a média dos juros que o Governo paga aos bancos que lhe emprestaram dinheiro. Refere-se à média do mês. Serve de referência para outras taxas de juros do país. A taxa Selic é a taxa básica de juros da economia.",
  "SERATUALIZACAO": "2020-11-20T05:08:00.403-03:00",
  "BASNOME": "Macroeconômico",
  "FNTID": 1333430857,
  "FNTSIGLA": "Bacen/Boletim/M. Finan.",
  "FNTNOME": "Banco Central do Brasil, Boletim, Seção mercado financeiro e de capitais (Bacen/Boletim/M. Finan.)",
  "FNTURL": "http://www.bcb.gov.br",
  "PERNOME": "Mensal",
  "UNINOME": "(% a.m.)",
  "MULNOME": null,
  "SERSTATUS": "A",
  "TEMCODIGO": 39,
  "TEMNOME": "Financeiras",
  "TEMCODIGOPAI": null,
  "PAICODIGO": "BRA",
  "SERNUMERICA": true,
  "SERTEMBR": null,
  "SERTEMEST": null,
  "SERTEMMUN": null,
  "SERTEMAMC": null,
  "SERTEMMET": null,
  "SERMINDATA": "1974-01-01T00:00:00-02:00",
  "SERMAXDATA": "2020-11-01T00:00:00-03:00",
  "FNTEXTURL": null,
  "SERPROGRAMAGERADOR": null,
  "SERDECIMAIS": 4,
  "SERQNT": 563
}
